[
  {
    "case": "N_1000",
    "family": "MNL",
    "generated": {
      "model": "mnl",
      "N": 1000,
      "J": 4,
      "K": 6,
      "rho": 0.3,
      "random_coefficients": 0
    },
    "n_obs": 1000,
    "n_alternatives": 4,
    "n_variables": 6,
    "rho": 0.3,
    "n_parameters": 9,
    "parameters": [
      "B_X1",
      "B_X2",
      "B_X3",
      "B_X4",
      "B_X5",
      "B_X6",
      "ASC_ALT2",
      "ASC_ALT3",
      "ASC_ALT4"
    ],
    "consistent": "Yes",
    "runtime_policy": {
      "cpu_policy": "single-logical-core",
      "logical_cpu_affinity": [
        0
      ],
      "timing_scope": "estimation-plus-covariance",
      "thread_environment": {
        "OMP_NUM_THREADS": "1",
        "MKL_NUM_THREADS": "1",
        "OPENBLAS_NUM_THREADS": "1",
        "NUMEXPR_NUM_THREADS": "1",
        "BLIS_NUM_THREADS": "1",
        "VECLIB_MAXIMUM_THREADS": "1"
      },
      "xla_flags": "--xla_cpu_multi_thread_eigen=false intra_op_parallelism_threads=1",
      "torch_intraop_threads": 1,
      "torch_interop_threads": 1,
      "threadpools": [
        {
          "user_api": "openmp",
          "internal_api": "openmp",
          "num_threads": 1
        },
        {
          "user_api": "blas",
          "internal_api": "openblas",
          "num_threads": 1
        },
        {
          "user_api": "blas",
          "internal_api": "openblas",
          "num_threads": 1
        }
      ]
    },
    "backends": [
      {
        "backend": "torchdcm",
        "available": true,
        "total_s": 0.00552381994202733,
        "estimate_s": 0.0043816580437123775,
        "covariance_s": 0.0011421618983149529,
        "loglike": -608.8233770496951,
        "ll_diff": 0.0,
        "max_param_diff": 0.0,
        "max_prob_diff": 0.0,
        "max_cov_diff": 0.0,
        "max_se_diff": 0.0,
        "closure_evals": 16,
        "optimizer_iterations": 15,
        "runtime_repeats_s": [
          0.00552381994202733,
          0.005509720183908939,
          0.005638776812702417
        ],
        "message": ""
      },
      {
        "backend": "scipy_bfgs",
        "available": true,
        "total_s": 0.7669536010362208,
        "estimate_s": 0.6521664671599865,
        "covariance_s": 0.11478713387623429,
        "loglike": -608.8233770496595,
        "ll_diff": 3.558398020686582E-11,
        "max_param_diff": 3.7635541866309907E-7,
        "max_prob_diff": 4.047796869910414E-7,
        "max_cov_diff": 9.063669710596134E-10,
        "max_se_diff": 3.992785060913384E-9,
        "closure_evals": null,
        "optimizer_iterations": null,
        "runtime_repeats_s": [
          0.7671078401617706,
          0.7602940509095788,
          0.7669536010362208
        ],
        "message": "Desired error not necessarily achieved due to precision loss."
      },
      {
        "backend": "biogeme",
        "available": true,
        "total_s": 2.391096579376608,
        "estimate_s": 2.3910265802405775,
        "covariance_s": 0.00006999913603067398,
        "loglike": -608.8233777186949,
        "ll_diff": -6.689998599540559E-7,
        "max_param_diff": 0.00005998349971125805,
        "max_prob_diff": 0.000022458891765997357,
        "max_cov_diff": 8.433034705511433E-7,
        "max_se_diff": 0.000003075048331024899,
        "closure_evals": null,
        "optimizer_iterations": null,
        "runtime_repeats_s": [
          2.379331151023507,
          2.3914102246053517,
          2.391096579376608
        ],
        "message": ""
      },
      {
        "backend": "apollo",
        "available": true,
        "total_s": 0.45000000000000007,
        "estimate_s": 0.45000000000000007,
        "covariance_s": 0,
        "loglike": -608.8233770499522,
        "ll_diff": -2.5715962692629546E-10,
        "max_param_diff": 0.000001045146555078702,
        "max_prob_diff": 0.000001501785713009518,
        "max_cov_diff": 1.0916475765010425E-8,
        "max_se_diff": 3.9805728851982636E-8,
        "closure_evals": null,
        "optimizer_iterations": null,
        "runtime_repeats_s": [
          0.44800000000000006,
          0.45200000000000007,
          0.45000000000000007
        ],
        "message": "apollo_version=0.3.8"
      },
      {
        "backend": "mlogit",
        "available": true,
        "total_s": 0.03400000000000003,
        "estimate_s": 0.03300000000000003,
        "covariance_s": 0.0010000000000000009,
        "loglike": -608.8233770496604,
        "ll_diff": 3.467448550509289E-11,
        "max_param_diff": 3.768024805783643E-7,
        "max_prob_diff": 4.0478285423528604E-7,
        "max_cov_diff": 9.05133357154142E-10,
        "max_se_diff": 3.9854447797527115E-9,
        "closure_evals": null,
        "optimizer_iterations": null,
        "runtime_repeats_s": [
          0.03400000000000003,
          0.03300000000000003,
          0.03400000000000003
        ],
        "message": ""
      },
      {
        "backend": "gmnl",
        "available": true,
        "total_s": 0.14700000000000002,
        "estimate_s": 0.14700000000000002,
        "covariance_s": 0.0,
        "loglike": -608.8233770496604,
        "ll_diff": 3.467448550509289E-11,
        "max_param_diff": 3.7680247824689594E-7,
        "max_prob_diff": 4.0478285845413353E-7,
        "max_cov_diff": 8.559904139671115E-10,
        "max_se_diff": 3.796651548704233E-9,
        "closure_evals": null,
        "optimizer_iterations": null,
        "runtime_repeats_s": [
          0.14700000000000002,
          0.14600000000000002,
          0.14700000000000002
        ],
        "message": ""
      },
      {
        "backend": "xlogit",
        "available": true,
        "total_s": 0.009822066873311996,
        "estimate_s": 0.009821586776524782,
        "covariance_s": 4.800967872142792E-7,
        "loglike": -608.8233770631231,
        "ll_diff": -1.3428007150650956E-8,
        "max_param_diff": 0.000009640776091612846,
        "max_prob_diff": 0.000008506037460220828,
        "max_cov_diff": 2.1131751123471335E-8,
        "max_se_diff": 1.1117913092939524E-7,
        "closure_evals": null,
        "optimizer_iterations": null,
        "runtime_repeats_s": [
          0.009742137044668198,
          0.009830606169998646,
          0.009822066873311996
        ],
        "message": ""
      }
    ],
    "true_parameters": {
      "B_X1": -0.25,
      "B_X2": -0.42000000000000004,
      "B_X3": -0.5900000000000001,
      "B_X4": -0.76,
      "B_X5": -0.93,
      "B_X6": -1.1,
      "ASC_ALT2": -0.2333333333333333,
      "ASC_ALT3": -0.4666666666666666,
      "ASC_ALT4": -0.7
    },
    "runtime_repetitions": 3,
    "runtime_summary": "median",
    "worker_policy": "independent child process per backend repetition"
  },
  {
    "case": "N_10000",
    "family": "MNL",
    "generated": {
      "model": "mnl",
      "N": 10000,
      "J": 4,
      "K": 6,
      "rho": 0.3,
      "random_coefficients": 0
    },
    "n_obs": 10000,
    "n_alternatives": 4,
    "n_variables": 6,
    "rho": 0.3,
    "n_parameters": 9,
    "parameters": [
      "B_X1",
      "B_X2",
      "B_X3",
      "B_X4",
      "B_X5",
      "B_X6",
      "ASC_ALT2",
      "ASC_ALT3",
      "ASC_ALT4"
    ],
    "consistent": "Yes",
    "runtime_policy": {
      "cpu_policy": "single-logical-core",
      "logical_cpu_affinity": [
        0
      ],
      "timing_scope": "estimation-plus-covariance",
      "thread_environment": {
        "OMP_NUM_THREADS": "1",
        "MKL_NUM_THREADS": "1",
        "OPENBLAS_NUM_THREADS": "1",
        "NUMEXPR_NUM_THREADS": "1",
        "BLIS_NUM_THREADS": "1",
        "VECLIB_MAXIMUM_THREADS": "1"
      },
      "xla_flags": "--xla_cpu_multi_thread_eigen=false intra_op_parallelism_threads=1",
      "torch_intraop_threads": 1,
      "torch_interop_threads": 1,
      "threadpools": [
        {
          "user_api": "openmp",
          "internal_api": "openmp",
          "num_threads": 1
        },
        {
          "user_api": "blas",
          "internal_api": "openblas",
          "num_threads": 1
        },
        {
          "user_api": "blas",
          "internal_api": "openblas",
          "num_threads": 1
        }
      ]
    },
    "backends": [
      {
        "backend": "torchdcm",
        "available": true,
        "total_s": 0.01464469963684678,
        "estimate_s": 0.010964227840304375,
        "covariance_s": 0.003680471796542406,
        "loglike": -6046.345299223956,
        "ll_diff": 0.0,
        "max_param_diff": 0.0,
        "max_prob_diff": 0.0,
        "max_cov_diff": 0.0,
        "max_se_diff": 0.0,
        "closure_evals": 17,
        "optimizer_iterations": 17,
        "runtime_repeats_s": [
          0.01464469963684678,
          0.014726289547979832,
          0.01462973142042756
        ],
        "message": ""
      },
      {
        "backend": "scipy_bfgs",
        "available": true,
        "total_s": 8.9460782087408,
        "estimate_s": 8.803048551548272,
        "covariance_s": 0.14302965719252825,
        "loglike": -6046.345299223943,
        "ll_diff": 1.3642420526593924E-11,
        "max_param_diff": 9.688831215104443E-8,
        "max_prob_diff": 1.3152841438213159E-7,
        "max_cov_diff": 6.626294369975472E-11,
        "max_se_diff": 9.638316186832974E-10,
        "closure_evals": null,
        "optimizer_iterations": null,
        "runtime_repeats_s": [
          8.953074127901345,
          8.894234695937485,
          8.9460782087408
        ],
        "message": "Desired error not necessarily achieved due to precision loss."
      },
      {
        "backend": "biogeme",
        "available": true,
        "total_s": 2.3765998324379325,
        "estimate_s": 2.3765301923267543,
        "covariance_s": 0.00006964011117815971,
        "loglike": -6046.345299223951,
        "ll_diff": 5.4569682106375694E-12,
        "max_param_diff": 4.3556160345126216E-8,
        "max_prob_diff": 6.154025034010857E-8,
        "max_cov_diff": 3.150241504289164E-11,
        "max_se_diff": 3.7498251032053176E-10,
        "closure_evals": null,
        "optimizer_iterations": null,
        "runtime_repeats_s": [
          2.3664252045564353,
          2.3765998324379325,
          2.3784644310362637
        ],
        "message": ""
      },
      {
        "backend": "apollo",
        "available": true,
        "total_s": 1.218,
        "estimate_s": 1.218,
        "covariance_s": 0,
        "loglike": -6046.345299223933,
        "ll_diff": 2.3646862246096134E-11,
        "max_param_diff": 9.971700698496733E-8,
        "max_prob_diff": 8.888411628937831E-8,
        "max_cov_diff": 4.1310415591772065E-11,
        "max_se_diff": 4.917300247542222E-10,
        "closure_evals": null,
        "optimizer_iterations": null,
        "runtime_repeats_s": [
          1.2159999999999997,
          1.2200000000000002,
          1.218
        ],
        "message": "apollo_version=0.3.8"
      },
      {
        "backend": "mlogit",
        "available": true,
        "total_s": 0.406,
        "estimate_s": 0.40500000000000014,
        "covariance_s": 0.0009999999999998899,
        "loglike": -6046.345299223951,
        "ll_diff": 5.4569682106375694E-12,
        "max_param_diff": 4.331193503848141E-8,
        "max_prob_diff": 6.154206455555311E-8,
        "max_cov_diff": 2.5044257683307092E-11,
        "max_se_diff": 2.9810916235550877E-10,
        "closure_evals": null,
        "optimizer_iterations": null,
        "runtime_repeats_s": [
          0.40900000000000014,
          0.406,
          0.40500000000000014
        ],
        "message": ""
      },
      {
        "backend": "gmnl",
        "available": true,
        "total_s": 1.939,
        "estimate_s": 1.9380000000000002,
        "covariance_s": 0.0009999999999998899,
        "loglike": -6046.345299223951,
        "ll_diff": 5.4569682106375694E-12,
        "max_param_diff": 4.3311937591994365E-8,
        "max_prob_diff": 6.154206588782074E-8,
        "max_cov_diff": 3.130178820136276E-11,
        "max_se_diff": 3.7259439283898743E-10,
        "closure_evals": null,
        "optimizer_iterations": null,
        "runtime_repeats_s": [
          1.939,
          1.939,
          1.935
        ],
        "message": ""
      },
      {
        "backend": "xlogit",
        "available": true,
        "total_s": 0.07247049221768975,
        "estimate_s": 0.07246807217597961,
        "covariance_s": 0.000002420041710138321,
        "loglike": -6046.345299237817,
        "ll_diff": -1.3860699255019426E-8,
        "max_param_diff": 0.000002913473413634904,
        "max_prob_diff": 0.0000027073141076749963,
        "max_cov_diff": 2.7723125255955244E-9,
        "max_se_diff": 3.299963829972441E-8,
        "closure_evals": null,
        "optimizer_iterations": null,
        "runtime_repeats_s": [
          0.07211412489414215,
          0.07247049221768975,
          0.07249368214979768
        ],
        "message": ""
      }
    ],
    "true_parameters": {
      "B_X1": -0.25,
      "B_X2": -0.42000000000000004,
      "B_X3": -0.5900000000000001,
      "B_X4": -0.76,
      "B_X5": -0.93,
      "B_X6": -1.1,
      "ASC_ALT2": -0.2333333333333333,
      "ASC_ALT3": -0.4666666666666666,
      "ASC_ALT4": -0.7
    },
    "runtime_repetitions": 3,
    "runtime_summary": "median",
    "worker_policy": "independent child process per backend repetition"
  },
  {
    "case": "N_100000",
    "family": "MNL",
    "generated": {
      "model": "mnl",
      "N": 100000,
      "J": 4,
      "K": 6,
      "rho": 0.3,
      "random_coefficients": 0
    },
    "n_obs": 100000,
    "n_alternatives": 4,
    "n_variables": 6,
    "rho": 0.3,
    "n_parameters": 9,
    "parameters": [
      "B_X1",
      "B_X2",
      "B_X3",
      "B_X4",
      "B_X5",
      "B_X6",
      "ASC_ALT2",
      "ASC_ALT3",
      "ASC_ALT4"
    ],
    "consistent": "Yes",
    "runtime_policy": {
      "cpu_policy": "single-logical-core",
      "logical_cpu_affinity": [
        0
      ],
      "timing_scope": "estimation-plus-covariance",
      "thread_environment": {
        "OMP_NUM_THREADS": "1",
        "MKL_NUM_THREADS": "1",
        "OPENBLAS_NUM_THREADS": "1",
        "NUMEXPR_NUM_THREADS": "1",
        "BLIS_NUM_THREADS": "1",
        "VECLIB_MAXIMUM_THREADS": "1"
      },
      "xla_flags": "--xla_cpu_multi_thread_eigen=false intra_op_parallelism_threads=1",
      "torch_intraop_threads": 1,
      "torch_interop_threads": 1,
      "threadpools": [
        {
          "user_api": "openmp",
          "internal_api": "openmp",
          "num_threads": 1
        },
        {
          "user_api": "blas",
          "internal_api": "openblas",
          "num_threads": 1
        },
        {
          "user_api": "blas",
          "internal_api": "openblas",
          "num_threads": 1
        }
      ]
    },
    "backends": [
      {
        "backend": "torchdcm",
        "available": true,
        "total_s": 0.13210856029763818,
        "estimate_s": 0.09440312022343278,
        "covariance_s": 0.0377054400742054,
        "loglike": -60967.29849147926,
        "ll_diff": 0.0,
        "max_param_diff": 0.0,
        "max_prob_diff": 0.0,
        "max_cov_diff": 0.0,
        "max_se_diff": 0.0,
        "closure_evals": 17,
        "optimizer_iterations": 17,
        "runtime_repeats_s": [
          0.13210856029763818,
          0.13180754287168384,
          0.1330583542585373
        ],
        "message": ""
      },
      {
        "backend": "scipy_bfgs",
        "available": true,
        "total_s": 105.60551664419472,
        "estimate_s": 105.42640219209716,
        "covariance_s": 0.17911445209756494,
        "loglike": -60967.298491479014,
        "ll_diff": 2.473825588822365E-10,
        "max_param_diff": 1.029975374988723E-7,
        "max_prob_diff": 1.267521377856795E-7,
        "max_cov_diff": 9.917140540846234E-12,
        "max_se_diff": 3.6435359417053004E-10,
        "closure_evals": null,
        "optimizer_iterations": null,
        "runtime_repeats_s": [
          105.50770980399102,
          105.60551664419472,
          105.72709050402045
        ],
        "message": "Desired error not necessarily achieved due to precision loss."
      },
      {
        "backend": "biogeme",
        "available": true,
        "total_s": 3.9456061273813248,
        "estimate_s": 3.9455332281067967,
        "covariance_s": 0.00007289927452802658,
        "loglike": -60967.29849147926,
        "ll_diff": 0.0,
        "max_param_diff": 9.484379781543595E-9,
        "max_prob_diff": 8.487105684906737E-9,
        "max_cov_diff": 6.544461424607545E-13,
        "max_se_diff": 2.555553338390304E-11,
        "closure_evals": null,
        "optimizer_iterations": null,
        "runtime_repeats_s": [
          3.9571563247591257,
          3.9456061273813248,
          3.9226027787663043
        ],
        "message": ""
      },
      {
        "backend": "apollo",
        "available": true,
        "total_s": 20.08,
        "estimate_s": 20.08,
        "covariance_s": 0,
        "loglike": -60967.29849147872,
        "ll_diff": 5.384208634495735E-10,
        "max_param_diff": 7.700053039627619E-8,
        "max_prob_diff": 5.784671158748367E-8,
        "max_cov_diff": 1.941105967368656E-12,
        "max_se_diff": 7.579844391036872E-11,
        "closure_evals": null,
        "optimizer_iterations": null,
        "runtime_repeats_s": [
          20.08,
          20.072000000000003,
          20.125999999999998
        ],
        "message": "apollo_version=0.3.8"
      },
      {
        "backend": "mlogit",
        "available": true,
        "total_s": 3.324,
        "estimate_s": 3.3229999999999995,
        "covariance_s": 0.001000000000000334,
        "loglike": -60967.29849147926,
        "ll_diff": 0.0,
        "max_param_diff": 9.484413865390451E-9,
        "max_prob_diff": 8.492214487176852E-9,
        "max_cov_diff": 1.205334280735687E-12,
        "max_se_diff": 4.7067221647933977E-11,
        "closure_evals": null,
        "optimizer_iterations": null,
        "runtime_repeats_s": [
          3.322,
          3.3310000000000004,
          3.324
        ],
        "message": ""
      },
      {
        "backend": "gmnl",
        "available": true,
        "total_s": 15.360999999999999,
        "estimate_s": 15.360999999999999,
        "covariance_s": 0.0,
        "loglike": -60967.29849147926,
        "ll_diff": 0.0,
        "max_param_diff": 9.484414614790992E-9,
        "max_prob_diff": 8.49221526433297E-9,
        "max_cov_diff": 6.683091851190232E-13,
        "max_se_diff": 2.6096872926539838E-11,
        "closure_evals": null,
        "optimizer_iterations": null,
        "runtime_repeats_s": [
          15.375,
          15.360999999999999,
          15.317
        ],
        "message": ""
      },
      {
        "backend": "xlogit",
        "available": true,
        "total_s": 0.771358510479331,
        "estimate_s": 0.7713575102388859,
        "covariance_s": 0.000001000240445137024,
        "loglike": -60967.29849147973,
        "ll_diff": -4.656612873077393E-10,
        "max_param_diff": 2.4705376755473907E-7,
        "max_prob_diff": 1.7236669525022563E-7,
        "max_cov_diff": 1.005553493661597E-11,
        "max_se_diff": 3.694381727620266E-10,
        "closure_evals": null,
        "optimizer_iterations": null,
        "runtime_repeats_s": [
          0.771358510479331,
          0.756989061832428,
          0.777836874127388
        ],
        "message": ""
      }
    ],
    "true_parameters": {
      "B_X1": -0.25,
      "B_X2": -0.42000000000000004,
      "B_X3": -0.5900000000000001,
      "B_X4": -0.76,
      "B_X5": -0.93,
      "B_X6": -1.1,
      "ASC_ALT2": -0.2333333333333333,
      "ASC_ALT3": -0.4666666666666666,
      "ASC_ALT4": -0.7
    },
    "runtime_repetitions": 3,
    "runtime_summary": "median",
    "worker_policy": "independent child process per backend repetition"
  },
  {
    "case": "J_3",
    "family": "MNL",
    "generated": {
      "model": "mnl",
      "N": 20000,
      "J": 3,
      "K": 6,
      "rho": 0.3,
      "random_coefficients": 0
    },
    "n_obs": 20000,
    "n_alternatives": 3,
    "n_variables": 6,
    "rho": 0.3,
    "n_parameters": 8,
    "parameters": [
      "B_X1",
      "B_X2",
      "B_X3",
      "B_X4",
      "B_X5",
      "B_X6",
      "ASC_ALT2",
      "ASC_ALT3"
    ],
    "consistent": "Yes",
    "runtime_policy": {
      "cpu_policy": "single-logical-core",
      "logical_cpu_affinity": [
        0
      ],
      "timing_scope": "estimation-plus-covariance",
      "thread_environment": {
        "OMP_NUM_THREADS": "1",
        "MKL_NUM_THREADS": "1",
        "OPENBLAS_NUM_THREADS": "1",
        "NUMEXPR_NUM_THREADS": "1",
        "BLIS_NUM_THREADS": "1",
        "VECLIB_MAXIMUM_THREADS": "1"
      },
      "xla_flags": "--xla_cpu_multi_thread_eigen=false intra_op_parallelism_threads=1",
      "torch_intraop_threads": 1,
      "torch_interop_threads": 1,
      "threadpools": [
        {
          "user_api": "openmp",
          "internal_api": "openmp",
          "num_threads": 1
        },
        {
          "user_api": "blas",
          "internal_api": "openblas",
          "num_threads": 1
        },
        {
          "user_api": "blas",
          "internal_api": "openblas",
          "num_threads": 1
        }
      ]
    },
    "backends": [
      {
        "backend": "torchdcm",
        "available": true,
        "total_s": 0.022444823291152716,
        "estimate_s": 0.01647115219384432,
        "covariance_s": 0.005973671097308397,
        "loglike": -9737.839836267882,
        "ll_diff": 0.0,
        "max_param_diff": 0.0,
        "max_prob_diff": 0.0,
        "max_cov_diff": 0.0,
        "max_se_diff": 0.0,
        "message": ""
      },
      {
        "backend": "scipy_bfgs",
        "available": true,
        "total_s": 23.64876226335764,
        "estimate_s": 23.64220630703494,
        "covariance_s": 0.006555956322699785,
        "loglike": -9737.839836267825,
        "ll_diff": 5.638867150992155E-11,
        "max_param_diff": 3.406547766093837E-8,
        "max_prob_diff": 2.0516106369328213E-8,
        "max_cov_diff": 1.1025626375435471E-11,
        "max_se_diff": 2.0251331167564501E-10,
        "message": "Desired error not necessarily achieved due to precision loss."
      },
      {
        "backend": "biogeme",
        "available": true,
        "total_s": 1.8247188501991332,
        "estimate_s": 1.824652521405369,
        "covariance_s": 0.00006632879376411438,
        "loglike": -9737.839836267878,
        "ll_diff": 3.637978807091713E-12,
        "max_param_diff": 4.0955447477841744E-8,
        "max_prob_diff": 2.5056002384005183E-8,
        "max_cov_diff": 1.909419215621877E-11,
        "max_se_diff": 3.5071278173259834E-10,
        "message": ""
      },
      {
        "backend": "apollo",
        "available": true,
        "total_s": 1.9869999999999999,
        "estimate_s": 1.9869999999999999,
        "covariance_s": 0,
        "loglike": -9737.839836267867,
        "ll_diff": 1.4551915228366852E-11,
        "max_param_diff": 9.069919970627893E-8,
        "max_prob_diff": 1.716073201318835E-7,
        "max_cov_diff": 1.800943340854802E-11,
        "max_se_diff": 4.907410311449922E-10,
        "message": "apollo_version=0.3.8"
      },
      {
        "backend": "mlogit",
        "available": true,
        "total_s": 0.6579999999999999,
        "estimate_s": 0.657,
        "covariance_s": 0.0009999999999998899,
        "loglike": -9737.839836267878,
        "ll_diff": 3.637978807091713E-12,
        "max_param_diff": 4.0955354219107676E-8,
        "max_prob_diff": 2.5058429331537013E-8,
        "max_cov_diff": 1.005225904685686E-11,
        "max_se_diff": 1.8463497744591884E-10,
        "message": ""
      },
      {
        "backend": "gmnl",
        "available": true,
        "total_s": 2.835,
        "estimate_s": 2.835,
        "covariance_s": 0.0,
        "loglike": -9737.83983626788,
        "ll_diff": 1.8189894035458565E-12,
        "max_param_diff": 4.095535044434939E-8,
        "max_prob_diff": 2.5058434327540624E-8,
        "max_cov_diff": 1.902062502726759E-11,
        "max_se_diff": 3.4936153622822097E-10,
        "message": ""
      },
      {
        "backend": "xlogit",
        "available": true,
        "total_s": 0.09259666921570897,
        "estimate_s": 0.09259621892124414,
        "covariance_s": 4.5029446482658386E-7,
        "loglike": -9737.839836269415,
        "ll_diff": -1.533408067189157E-9,
        "max_param_diff": 7.087884659195964E-7,
        "max_prob_diff": 6.329057569143259E-7,
        "max_cov_diff": 3.182963978108286E-10,
        "max_se_diff": 7.57533127893062E-9,
        "message": ""
      }
    ],
    "true_parameters": {
      "B_X1": -0.25,
      "B_X2": -0.42000000000000004,
      "B_X3": -0.5900000000000001,
      "B_X4": -0.76,
      "B_X5": -0.93,
      "B_X6": -1.1,
      "ASC_ALT2": -0.35,
      "ASC_ALT3": -0.7
    }
  },
  {
    "case": "J_10",
    "family": "MNL",
    "generated": {
      "model": "mnl",
      "N": 20000,
      "J": 10,
      "K": 6,
      "rho": 0.3,
      "random_coefficients": 0
    },
    "n_obs": 20000,
    "n_alternatives": 10,
    "n_variables": 6,
    "rho": 0.3,
    "n_parameters": 15,
    "parameters": [
      "B_X1",
      "B_X2",
      "B_X3",
      "B_X4",
      "B_X5",
      "B_X6",
      "ASC_ALT2",
      "ASC_ALT3",
      "ASC_ALT4",
      "ASC_ALT5",
      "ASC_ALT6",
      "ASC_ALT7",
      "ASC_ALT8",
      "ASC_ALT9",
      "ASC_ALT10"
    ],
    "consistent": "Yes",
    "runtime_policy": {
      "cpu_policy": "single-logical-core",
      "logical_cpu_affinity": [
        0
      ],
      "timing_scope": "estimation-plus-covariance",
      "thread_environment": {
        "OMP_NUM_THREADS": "1",
        "MKL_NUM_THREADS": "1",
        "OPENBLAS_NUM_THREADS": "1",
        "NUMEXPR_NUM_THREADS": "1",
        "BLIS_NUM_THREADS": "1",
        "VECLIB_MAXIMUM_THREADS": "1"
      },
      "xla_flags": "--xla_cpu_multi_thread_eigen=false intra_op_parallelism_threads=1",
      "torch_intraop_threads": 1,
      "torch_interop_threads": 1,
      "threadpools": [
        {
          "user_api": "openmp",
          "internal_api": "openmp",
          "num_threads": 1
        },
        {
          "user_api": "blas",
          "internal_api": "openblas",
          "num_threads": 1
        },
        {
          "user_api": "blas",
          "internal_api": "openblas",
          "num_threads": 1
        }
      ]
    },
    "backends": [
      {
        "backend": "torchdcm",
        "available": true,
        "total_s": 0.10639400454238057,
        "estimate_s": 0.07687662681564689,
        "covariance_s": 0.029517377726733685,
        "loglike": -20860.252427214215,
        "ll_diff": 0.0,
        "max_param_diff": 0.0,
        "max_prob_diff": 0.0,
        "max_cov_diff": 0.0,
        "max_se_diff": 0.0,
        "message": ""
      },
      {
        "backend": "scipy_bfgs",
        "available": true,
        "total_s": 25.440410506911576,
        "estimate_s": 25.410299321170896,
        "covariance_s": 0.030111185740679502,
        "loglike": -20860.2524272138,
        "ll_diff": 4.147295840084553E-10,
        "max_param_diff": 1.769791911909735E-7,
        "max_prob_diff": 2.9921299621316066E-7,
        "max_cov_diff": 5.075452016133075E-11,
        "max_se_diff": 6.301414876008771E-10,
        "message": "Desired error not necessarily achieved due to precision loss."
      },
      {
        "backend": "biogeme",
        "available": true,
        "total_s": 7.133926754351705,
        "estimate_s": 7.133840015158057,
        "covariance_s": 0.0000867391936480999,
        "loglike": -20860.25242729672,
        "ll_diff": -8.250572136603296E-8,
        "max_param_diff": 0.0000032689780322670003,
        "max_prob_diff": 0.0000018973130936350557,
        "max_cov_diff": 4.1828599401435435E-9,
        "max_se_diff": 4.867340065023429E-8,
        "message": ""
      },
      {
        "backend": "apollo",
        "available": true,
        "total_s": 7.840000000000001,
        "estimate_s": 7.840000000000001,
        "covariance_s": 0,
        "loglike": -20860.25242721414,
        "ll_diff": 7.275957614183426E-11,
        "max_param_diff": 3.1580461637426005E-7,
        "max_prob_diff": 3.406491814184065E-7,
        "max_cov_diff": 6.724859211160172E-11,
        "max_se_diff": 8.249261343462599E-10,
        "message": "apollo_version=0.3.8"
      },
      {
        "backend": "mlogit",
        "available": true,
        "total_s": 1.862,
        "estimate_s": 1.8609999999999998,
        "covariance_s": 0.001000000000000334,
        "loglike": -20860.25242721395,
        "ll_diff": 2.6557245291769505E-10,
        "max_param_diff": 1.7696525778099215E-7,
        "max_prob_diff": 2.9924036903938855E-7,
        "max_cov_diff": 5.0738798362467974E-11,
        "max_se_diff": 6.299462965153602E-10,
        "message": ""
      },
      {
        "backend": "gmnl",
        "available": true,
        "total_s": 25.229000000000003,
        "estimate_s": 25.229000000000003,
        "covariance_s": 0.0,
        "loglike": -20860.25242721395,
        "ll_diff": 2.6557245291769505E-10,
        "max_param_diff": 1.7696525789201445E-7,
        "max_prob_diff": 2.99240369205922E-7,
        "max_cov_diff": 5.0573250665389424E-11,
        "max_se_diff": 6.278909406298716E-10,
        "message": ""
      },
      {
        "backend": "xlogit",
        "available": true,
        "total_s": 0.7360860942862928,
        "estimate_s": 0.7360852439887822,
        "covariance_s": 8.502975106239319E-7,
        "loglike": -20860.252427214145,
        "ll_diff": 6.912159733474255E-11,
        "max_param_diff": 3.719754572695244E-7,
        "max_prob_diff": 4.245089140764158E-7,
        "max_cov_diff": 4.66930329687601E-10,
        "max_se_diff": 5.797161604925716E-9,
        "message": ""
      }
    ],
    "true_parameters": {
      "B_X1": -0.25,
      "B_X2": -0.42000000000000004,
      "B_X3": -0.5900000000000001,
      "B_X4": -0.76,
      "B_X5": -0.93,
      "B_X6": -1.1,
      "ASC_ALT2": -0.07777777777777778,
      "ASC_ALT3": -0.15555555555555556,
      "ASC_ALT4": -0.23333333333333334,
      "ASC_ALT5": -0.3111111111111111,
      "ASC_ALT6": -0.3888888888888889,
      "ASC_ALT7": -0.4666666666666667,
      "ASC_ALT8": -0.5444444444444445,
      "ASC_ALT9": -0.6222222222222222,
      "ASC_ALT10": -0.7
    }
  },
  {
    "case": "J_20",
    "family": "MNL",
    "generated": {
      "model": "mnl",
      "N": 20000,
      "J": 20,
      "K": 6,
      "rho": 0.3,
      "random_coefficients": 0
    },
    "n_obs": 20000,
    "n_alternatives": 20,
    "n_variables": 6,
    "rho": 0.3,
    "n_parameters": 25,
    "parameters": [
      "B_X1",
      "B_X2",
      "B_X3",
      "B_X4",
      "B_X5",
      "B_X6",
      "ASC_ALT2",
      "ASC_ALT3",
      "ASC_ALT4",
      "ASC_ALT5",
      "ASC_ALT6",
      "ASC_ALT7",
      "ASC_ALT8",
      "ASC_ALT9",
      "ASC_ALT10",
      "ASC_ALT11",
      "ASC_ALT12",
      "ASC_ALT13",
      "ASC_ALT14",
      "ASC_ALT15",
      "ASC_ALT16",
      "ASC_ALT17",
      "ASC_ALT18",
      "ASC_ALT19",
      "ASC_ALT20"
    ],
    "consistent": "Yes",
    "runtime_policy": {
      "cpu_policy": "single-logical-core",
      "logical_cpu_affinity": [
        0
      ],
      "timing_scope": "estimation-plus-covariance",
      "thread_environment": {
        "OMP_NUM_THREADS": "1",
        "MKL_NUM_THREADS": "1",
        "OPENBLAS_NUM_THREADS": "1",
        "NUMEXPR_NUM_THREADS": "1",
        "BLIS_NUM_THREADS": "1",
        "VECLIB_MAXIMUM_THREADS": "1"
      },
      "xla_flags": "--xla_cpu_multi_thread_eigen=false intra_op_parallelism_threads=1",
      "torch_intraop_threads": 1,
      "torch_interop_threads": 1,
      "threadpools": [
        {
          "user_api": "openmp",
          "internal_api": "openmp",
          "num_threads": 1
        },
        {
          "user_api": "blas",
          "internal_api": "openblas",
          "num_threads": 1
        },
        {
          "user_api": "blas",
          "internal_api": "openblas",
          "num_threads": 1
        }
      ]
    },
    "backends": [
      {
        "backend": "torchdcm",
        "available": true,
        "total_s": 0.47806695709005,
        "estimate_s": 0.30967588210478425,
        "covariance_s": 0.16839107498526573,
        "loglike": -27835.174509003056,
        "ll_diff": 0.0,
        "max_param_diff": 0.0,
        "max_prob_diff": 0.0,
        "max_cov_diff": 0.0,
        "max_se_diff": 0.0,
        "message": ""
      },
      {
        "backend": "scipy_bfgs",
        "available": true,
        "total_s": 22.153300334699452,
        "estimate_s": 21.982114830985665,
        "covariance_s": 0.1711855037137866,
        "loglike": -27835.174509002987,
        "ll_diff": 6.912159733474255E-11,
        "max_param_diff": 1.6528135515780917E-7,
        "max_prob_diff": 5.85394676066997E-8,
        "max_cov_diff": 1.600956927791386E-10,
        "max_se_diff": 1.4070198756099828E-9,
        "message": "Desired error not necessarily achieved due to precision loss."
      },
      {
        "backend": "biogeme",
        "available": true,
        "total_s": 24.138115214649588,
        "estimate_s": 24.137983525637537,
        "covariance_s": 0.00013168901205062866,
        "loglike": -27835.174509003555,
        "ll_diff": -4.984030965715647E-10,
        "max_param_diff": 2.4465343673174544E-7,
        "max_prob_diff": 1.848194528530911E-7,
        "max_cov_diff": 4.963297108376286E-10,
        "max_se_diff": 4.34897872575446E-9,
        "message": ""
      },
      {
        "backend": "apollo",
        "available": true,
        "total_s": 30.662000000000003,
        "estimate_s": 30.662000000000003,
        "covariance_s": 0,
        "loglike": -27835.174509003133,
        "ll_diff": -7.639755494892597E-11,
        "max_param_diff": 2.3539073418232803E-7,
        "max_prob_diff": 1.3480602462090374E-7,
        "max_cov_diff": 3.5774249838513295E-10,
        "max_se_diff": 3.2645966624444966E-9,
        "message": "apollo_version=0.3.8"
      },
      {
        "backend": "mlogit",
        "available": true,
        "total_s": 4.276000000000001,
        "estimate_s": 4.2749999999999995,
        "covariance_s": 0.0010000000000012221,
        "loglike": -27835.174509003027,
        "ll_diff": 2.9103830456733704E-11,
        "max_param_diff": 2.4541313992099134E-7,
        "max_prob_diff": 1.8514649657852544E-7,
        "max_cov_diff": 2.01903179505164E-10,
        "max_se_diff": 1.7744498995164726E-9,
        "message": ""
      },
      {
        "backend": "gmnl",
        "available": true,
        "total_s": 113.837,
        "estimate_s": 113.837,
        "covariance_s": 0.0,
        "loglike": -27835.174509003027,
        "ll_diff": 2.9103830456733704E-11,
        "max_param_diff": 1.815655776282732E-7,
        "max_prob_diff": 6.586704692779222E-8,
        "max_cov_diff": 2.0248553658439028E-10,
        "max_se_diff": 1.7795680137822067E-9,
        "message": ""
      },
      {
        "backend": "xlogit",
        "available": true,
        "total_s": 4.379374341107905,
        "estimate_s": 4.3793736710213125,
        "covariance_s": 6.700865924358368E-7,
        "loglike": -27835.17450900409,
        "ll_diff": -1.0331859812140465E-9,
        "max_param_diff": 5.745822478919749E-7,
        "max_prob_diff": 3.1725983540287217E-7,
        "max_cov_diff": 1.0880167869084523E-9,
        "max_se_diff": 9.64038716216864E-9,
        "message": ""
      }
    ],
    "true_parameters": {
      "B_X1": -0.25,
      "B_X2": -0.42000000000000004,
      "B_X3": -0.5900000000000001,
      "B_X4": -0.76,
      "B_X5": -0.93,
      "B_X6": -1.1,
      "ASC_ALT2": -0.0368421052631579,
      "ASC_ALT3": -0.0736842105263158,
      "ASC_ALT4": -0.11052631578947367,
      "ASC_ALT5": -0.14736842105263157,
      "ASC_ALT6": -0.18421052631578946,
      "ASC_ALT7": -0.22105263157894733,
      "ASC_ALT8": -0.25789473684210523,
      "ASC_ALT9": -0.29473684210526313,
      "ASC_ALT10": -0.33157894736842103,
      "ASC_ALT11": -0.3684210526315789,
      "ASC_ALT12": -0.4052631578947368,
      "ASC_ALT13": -0.44210526315789467,
      "ASC_ALT14": -0.47894736842105257,
      "ASC_ALT15": -0.5157894736842105,
      "ASC_ALT16": -0.5526315789473684,
      "ASC_ALT17": -0.5894736842105263,
      "ASC_ALT18": -0.6263157894736842,
      "ASC_ALT19": -0.6631578947368421,
      "ASC_ALT20": -0.7
    }
  },
  {
    "case": "K_4",
    "family": "MNL",
    "generated": {
      "model": "mnl",
      "N": 20000,
      "J": 5,
      "K": 4,
      "rho": 0.3,
      "random_coefficients": 0
    },
    "n_obs": 20000,
    "n_alternatives": 5,
    "n_variables": 4,
    "rho": 0.3,
    "n_parameters": 8,
    "parameters": [
      "B_X1",
      "B_X2",
      "B_X3",
      "B_X4",
      "ASC_ALT2",
      "ASC_ALT3",
      "ASC_ALT4",
      "ASC_ALT5"
    ],
    "consistent": "Yes",
    "runtime_policy": {
      "cpu_policy": "single-logical-core",
      "logical_cpu_affinity": [
        0
      ],
      "timing_scope": "estimation-plus-covariance",
      "thread_environment": {
        "OMP_NUM_THREADS": "1",
        "MKL_NUM_THREADS": "1",
        "OPENBLAS_NUM_THREADS": "1",
        "NUMEXPR_NUM_THREADS": "1",
        "BLIS_NUM_THREADS": "1",
        "VECLIB_MAXIMUM_THREADS": "1"
      },
      "xla_flags": "--xla_cpu_multi_thread_eigen=false intra_op_parallelism_threads=1",
      "torch_intraop_threads": 1,
      "torch_interop_threads": 1,
      "threadpools": [
        {
          "user_api": "openmp",
          "internal_api": "openmp",
          "num_threads": 1
        },
        {
          "user_api": "blas",
          "internal_api": "openblas",
          "num_threads": 1
        },
        {
          "user_api": "blas",
          "internal_api": "openblas",
          "num_threads": 1
        }
      ]
    },
    "backends": [
      {
        "backend": "torchdcm",
        "available": true,
        "total_s": 0.025699445977807045,
        "estimate_s": 0.019521017093211412,
        "covariance_s": 0.0061784288845956326,
        "loglike": -18328.433974536412,
        "ll_diff": 0.0,
        "max_param_diff": 0.0,
        "max_prob_diff": 0.0,
        "max_cov_diff": 0.0,
        "max_se_diff": 0.0,
        "message": ""
      },
      {
        "backend": "scipy_bfgs",
        "available": true,
        "total_s": 10.642543632071465,
        "estimate_s": 10.635812558233738,
        "covariance_s": 0.006731073837727308,
        "loglike": -18328.433974536263,
        "ll_diff": 1.4915713109076023E-10,
        "max_param_diff": 2.491721060593477E-7,
        "max_prob_diff": 1.7195700702243855E-7,
        "max_cov_diff": 5.110806179306482E-11,
        "max_se_diff": 9.488617253028409E-10,
        "message": "Desired error not necessarily achieved due to precision loss."
      },
      {
        "backend": "biogeme",
        "available": true,
        "total_s": 2.0191207914613187,
        "estimate_s": 2.0190507024526596,
        "covariance_s": 0.00007008900865912437,
        "loglike": -18328.433974536318,
        "ll_diff": 9.458744898438454E-11,
        "max_param_diff": 2.8752813463484017E-7,
        "max_prob_diff": 1.6226165810984128E-7,
        "max_cov_diff": 3.988491427322355E-11,
        "max_se_diff": 6.805269646414924E-10,
        "message": ""
      },
      {
        "backend": "apollo",
        "available": true,
        "total_s": 2.091,
        "estimate_s": 2.091,
        "covariance_s": 0,
        "loglike": -18328.433974536478,
        "ll_diff": -6.548361852765083E-11,
        "max_param_diff": 2.7589050466403364E-7,
        "max_prob_diff": 2.242347209024942E-7,
        "max_cov_diff": 8.977776551691297E-11,
        "max_se_diff": 1.6667954412519226E-9,
        "message": "apollo_version=0.3.8"
      },
      {
        "backend": "mlogit",
        "available": true,
        "total_s": 0.8530000000000001,
        "estimate_s": 0.85,
        "covariance_s": 0.0030000000000001137,
        "loglike": -18328.4339745363,
        "ll_diff": 1.127773430198431E-10,
        "max_param_diff": 2.8752813463484017E-7,
        "max_prob_diff": 1.6226165844290819E-7,
        "max_cov_diff": 5.1385445811596986E-11,
        "max_se_diff": 9.540115815387384E-10,
        "message": ""
      },
      {
        "backend": "gmnl",
        "available": true,
        "total_s": 4.141,
        "estimate_s": 4.141,
        "covariance_s": 0.0,
        "loglike": -18328.4339745363,
        "ll_diff": 1.127773430198431E-10,
        "max_param_diff": 2.501739284621607E-7,
        "max_prob_diff": 1.7248192563101838E-7,
        "max_cov_diff": 5.144640215139912E-11,
        "max_se_diff": 9.551432839094431E-10,
        "message": ""
      },
      {
        "backend": "xlogit",
        "available": true,
        "total_s": 0.1361577259376645,
        "estimate_s": 0.13615719601511955,
        "covariance_s": 5.299225449562073E-7,
        "loglike": -18328.433974536536,
        "ll_diff": -1.2369127944111824E-10,
        "max_param_diff": 4.3338311361829085E-7,
        "max_prob_diff": 2.4299722423126724E-7,
        "max_cov_diff": 1.4558911107936945E-10,
        "max_se_diff": 2.702977300317322E-9,
        "message": ""
      }
    ],
    "true_parameters": {
      "B_X1": -0.25,
      "B_X2": -0.5333333333333334,
      "B_X3": -0.8166666666666668,
      "B_X4": -1.1,
      "ASC_ALT2": -0.175,
      "ASC_ALT3": -0.35,
      "ASC_ALT4": -0.5249999999999999,
      "ASC_ALT5": -0.7
    }
  },
  {
    "case": "K_12",
    "family": "MNL",
    "generated": {
      "model": "mnl",
      "N": 20000,
      "J": 5,
      "K": 12,
      "rho": 0.3,
      "random_coefficients": 0
    },
    "n_obs": 20000,
    "n_alternatives": 5,
    "n_variables": 12,
    "rho": 0.3,
    "n_parameters": 16,
    "parameters": [
      "B_X1",
      "B_X2",
      "B_X3",
      "B_X4",
      "B_X5",
      "B_X6",
      "B_X7",
      "B_X8",
      "B_X9",
      "B_X10",
      "B_X11",
      "B_X12",
      "ASC_ALT2",
      "ASC_ALT3",
      "ASC_ALT4",
      "ASC_ALT5"
    ],
    "consistent": "Yes",
    "runtime_policy": {
      "cpu_policy": "single-logical-core",
      "logical_cpu_affinity": [
        0
      ],
      "timing_scope": "estimation-plus-covariance",
      "thread_environment": {
        "OMP_NUM_THREADS": "1",
        "MKL_NUM_THREADS": "1",
        "OPENBLAS_NUM_THREADS": "1",
        "NUMEXPR_NUM_THREADS": "1",
        "BLIS_NUM_THREADS": "1",
        "VECLIB_MAXIMUM_THREADS": "1"
      },
      "xla_flags": "--xla_cpu_multi_thread_eigen=false intra_op_parallelism_threads=1",
      "torch_intraop_threads": 1,
      "torch_interop_threads": 1,
      "threadpools": [
        {
          "user_api": "openmp",
          "internal_api": "openmp",
          "num_threads": 1
        },
        {
          "user_api": "blas",
          "internal_api": "openblas",
          "num_threads": 1
        },
        {
          "user_api": "blas",
          "internal_api": "openblas",
          "num_threads": 1
        }
      ]
    },
    "backends": [
      {
        "backend": "torchdcm",
        "available": true,
        "total_s": 0.0385893820784986,
        "estimate_s": 0.02548189088702202,
        "covariance_s": 0.013107491191476583,
        "loglike": -8083.607854015172,
        "ll_diff": 0.0,
        "max_param_diff": 0.0,
        "max_prob_diff": 0.0,
        "max_cov_diff": 0.0,
        "max_se_diff": 0.0,
        "message": ""
      },
      {
        "backend": "scipy_bfgs",
        "available": true,
        "total_s": 32.520896662957966,
        "estimate_s": 32.50691819796339,
        "covariance_s": 0.013978464994579554,
        "loglike": -8083.607854015103,
        "ll_diff": 6.912159733474255E-11,
        "max_param_diff": 1.6744711792138212E-7,
        "max_prob_diff": 1.1379388387133815E-7,
        "max_cov_diff": 6.225840372756086E-11,
        "max_se_diff": 7.228799364655814E-10,
        "message": "Desired error not necessarily achieved due to precision loss."
      },
      {
        "backend": "biogeme",
        "available": true,
        "total_s": 6.406963639426976,
        "estimate_s": 6.40686685917899,
        "covariance_s": 0.00009678024798631668,
        "loglike": -8083.607854015592,
        "ll_diff": -4.2018655221909285E-10,
        "max_param_diff": 3.792752463205318E-7,
        "max_prob_diff": 2.0569890468724594E-7,
        "max_cov_diff": 5.968503581990636E-10,
        "max_se_diff": 7.044101704711814E-9,
        "message": ""
      },
      {
        "backend": "apollo",
        "available": true,
        "total_s": 6.382,
        "estimate_s": 6.382,
        "covariance_s": 0,
        "loglike": -8083.607854015237,
        "ll_diff": -6.45741238258779E-11,
        "max_param_diff": 5.134029489040071E-7,
        "max_prob_diff": 2.9358113073918446E-7,
        "max_cov_diff": 8.386894412466817E-11,
        "max_se_diff": 1.0068833614096384E-9,
        "message": "apollo_version=0.3.8"
      },
      {
        "backend": "mlogit",
        "available": true,
        "total_s": 1.2189999999999999,
        "estimate_s": 1.218,
        "covariance_s": 0.0009999999999998899,
        "loglike": -8083.607854015144,
        "ll_diff": 2.8194335754960775E-11,
        "max_param_diff": 3.793027001375293E-7,
        "max_prob_diff": 2.057151329282192E-7,
        "max_cov_diff": 6.228697202112499E-11,
        "max_se_diff": 7.232116364108698E-10,
        "message": ""
      },
      {
        "backend": "gmnl",
        "available": true,
        "total_s": 17.757,
        "estimate_s": 17.757,
        "covariance_s": 0.0,
        "loglike": -8083.607854015144,
        "ll_diff": 2.8194335754960775E-11,
        "max_param_diff": 1.624714189296661E-7,
        "max_prob_diff": 1.0766752522872736E-7,
        "max_cov_diff": 6.256797662439195E-11,
        "max_se_diff": 7.26474373713426E-10,
        "message": ""
      },
      {
        "backend": "xlogit",
        "available": true,
        "total_s": 0.4446842661127448,
        "estimate_s": 0.44468377623707056,
        "covariance_s": 4.898756742477417E-7,
        "loglike": -8083.607854172686,
        "ll_diff": -1.575135684106499E-7,
        "max_param_diff": 0.0000087933351127778,
        "max_prob_diff": 0.00000867501903667467,
        "max_cov_diff": 5.065465272712996E-9,
        "max_se_diff": 5.978328447564518E-8,
        "message": ""
      }
    ],
    "true_parameters": {
      "B_X1": -0.25,
      "B_X2": -0.32727272727272727,
      "B_X3": -0.40454545454545454,
      "B_X4": -0.48181818181818187,
      "B_X5": -0.5590909090909091,
      "B_X6": -0.6363636363636365,
      "B_X7": -0.7136363636363637,
      "B_X8": -0.790909090909091,
      "B_X9": -0.8681818181818183,
      "B_X10": -0.9454545454545455,
      "B_X11": -1.022727272727273,
      "B_X12": -1.1,
      "ASC_ALT2": -0.175,
      "ASC_ALT3": -0.35,
      "ASC_ALT4": -0.5249999999999999,
      "ASC_ALT5": -0.7
    }
  },
  {
    "case": "K_32",
    "family": "MNL",
    "generated": {
      "model": "mnl",
      "N": 20000,
      "J": 5,
      "K": 32,
      "rho": 0.3,
      "random_coefficients": 0
    },
    "n_obs": 20000,
    "n_alternatives": 5,
    "n_variables": 32,
    "rho": 0.3,
    "n_parameters": 36,
    "parameters": [
      "B_X1",
      "B_X2",
      "B_X3",
      "B_X4",
      "B_X5",
      "B_X6",
      "B_X7",
      "B_X8",
      "B_X9",
      "B_X10",
      "B_X11",
      "B_X12",
      "B_X13",
      "B_X14",
      "B_X15",
      "B_X16",
      "B_X17",
      "B_X18",
      "B_X19",
      "B_X20",
      "B_X21",
      "B_X22",
      "B_X23",
      "B_X24",
      "B_X25",
      "B_X26",
      "B_X27",
      "B_X28",
      "B_X29",
      "B_X30",
      "B_X31",
      "B_X32",
      "ASC_ALT2",
      "ASC_ALT3",
      "ASC_ALT4",
      "ASC_ALT5"
    ],
    "consistent": "Yes",
    "runtime_policy": {
      "cpu_policy": "single-logical-core",
      "logical_cpu_affinity": [
        0
      ],
      "timing_scope": "estimation-plus-covariance",
      "thread_environment": {
        "OMP_NUM_THREADS": "1",
        "MKL_NUM_THREADS": "1",
        "OPENBLAS_NUM_THREADS": "1",
        "NUMEXPR_NUM_THREADS": "1",
        "BLIS_NUM_THREADS": "1",
        "VECLIB_MAXIMUM_THREADS": "1"
      },
      "xla_flags": "--xla_cpu_multi_thread_eigen=false intra_op_parallelism_threads=1",
      "torch_intraop_threads": 1,
      "torch_interop_threads": 1,
      "threadpools": [
        {
          "user_api": "openmp",
          "internal_api": "openmp",
          "num_threads": 1
        },
        {
          "user_api": "blas",
          "internal_api": "openblas",
          "num_threads": 1
        },
        {
          "user_api": "blas",
          "internal_api": "openblas",
          "num_threads": 1
        }
      ]
    },
    "backends": [
      {
        "backend": "torchdcm",
        "available": true,
        "total_s": 0.12835073983296752,
        "estimate_s": 0.06253382097929716,
        "covariance_s": 0.06581691885367036,
        "loglike": -3148.8405006320145,
        "ll_diff": 0.0,
        "max_param_diff": 0.0,
        "max_prob_diff": 0.0,
        "max_cov_diff": 0.0,
        "max_se_diff": 0.0,
        "message": ""
      },
      {
        "backend": "scipy_bfgs",
        "available": true,
        "total_s": 39.87836789805442,
        "estimate_s": 39.81363815208897,
        "covariance_s": 0.064729745965451,
        "loglike": -3148.840500631854,
        "ll_diff": 1.6052581486292183E-10,
        "max_param_diff": 6.040597165246631E-7,
        "max_prob_diff": 3.8161437165840084E-7,
        "max_cov_diff": 2.9649702311396187E-10,
        "max_se_diff": 2.2733119275919478E-9,
        "message": "Desired error not necessarily achieved due to precision loss."
      },
      {
        "backend": "biogeme",
        "available": true,
        "total_s": 42.51738059287891,
        "estimate_s": 42.51719427481294,
        "covariance_s": 0.0001863180659711361,
        "loglike": -3148.840500694268,
        "ll_diff": -6.225354809430428E-8,
        "max_param_diff": 0.000006992888378798412,
        "max_prob_diff": 0.0000028244034786517602,
        "max_cov_diff": 3.164033757739604E-8,
        "max_se_diff": 2.3253137325374151E-7,
        "message": ""
      },
      {
        "backend": "apollo",
        "available": true,
        "total_s": 34.958,
        "estimate_s": 34.958,
        "covariance_s": 0,
        "loglike": -3148.8405006328394,
        "ll_diff": -8.249116945080459E-10,
        "max_param_diff": 6.765796232155452E-7,
        "max_prob_diff": 0.0000012463506548487935,
        "max_cov_diff": 4.2773783646976593E-10,
        "max_se_diff": 5.044789596481136E-9,
        "message": "apollo_version=0.3.8"
      },
      {
        "backend": "mlogit",
        "available": true,
        "total_s": 2.2409999999999997,
        "estimate_s": 2.24,
        "covariance_s": 0.0009999999999994458,
        "loglike": -3148.8405006318576,
        "ll_diff": 1.5688783605583012E-10,
        "max_param_diff": 5.763466777164439E-7,
        "max_prob_diff": 3.642021890737368E-7,
        "max_cov_diff": 3.264690375676116E-10,
        "max_se_diff": 2.5031143685572133E-9,
        "message": ""
      },
      {
        "backend": "gmnl",
        "available": true,
        "total_s": 125.07000000000002,
        "estimate_s": 125.07000000000002,
        "covariance_s": 0.0,
        "loglike": -3148.840500631857,
        "ll_diff": 1.5734258340671659E-10,
        "max_param_diff": 5.763466774943993E-7,
        "max_prob_diff": 3.6420219040600443E-7,
        "max_cov_diff": 3.2616196722623503E-10,
        "max_se_diff": 2.5007599879778297E-9,
        "message": ""
      },
      {
        "backend": "xlogit",
        "available": true,
        "total_s": 3.208429962862283,
        "estimate_s": 3.2084293430671096,
        "covariance_s": 6.19795173406601E-7,
        "loglike": -3148.8405010768543,
        "ll_diff": -4.448397703527007E-7,
        "max_param_diff": 0.000013781997516115752,
        "max_prob_diff": 0.000024721359549062516,
        "max_cov_diff": 9.554049417055677E-9,
        "max_se_diff": 1.1382924024888608E-7,
        "message": ""
      }
    ],
    "true_parameters": {
      "B_X1": -0.25,
      "B_X2": -0.27741935483870966,
      "B_X3": -0.3048387096774194,
      "B_X4": -0.33225806451612905,
      "B_X5": -0.3596774193548387,
      "B_X6": -0.3870967741935484,
      "B_X7": -0.4145161290322581,
      "B_X8": -0.44193548387096776,
      "B_X9": -0.4693548387096774,
      "B_X10": -0.49677419354838714,
      "B_X11": -0.5241935483870968,
      "B_X12": -0.5516129032258065,
      "B_X13": -0.5790322580645162,
      "B_X14": -0.6064516129032258,
      "B_X15": -0.6338709677419355,
      "B_X16": -0.6612903225806452,
      "B_X17": -0.6887096774193548,
      "B_X18": -0.7161290322580646,
      "B_X19": -0.7435483870967743,
      "B_X20": -0.7709677419354839,
      "B_X21": -0.7983870967741936,
      "B_X22": -0.8258064516129033,
      "B_X23": -0.853225806451613,
      "B_X24": -0.8806451612903227,
      "B_X25": -0.9080645161290324,
      "B_X26": -0.935483870967742,
      "B_X27": -0.9629032258064517,
      "B_X28": -0.9903225806451614,
      "B_X29": -1.017741935483871,
      "B_X30": -1.0451612903225809,
      "B_X31": -1.0725806451612905,
      "B_X32": -1.1,
      "ASC_ALT2": -0.175,
      "ASC_ALT3": -0.35,
      "ASC_ALT4": -0.5249999999999999,
      "ASC_ALT5": -0.7
    }
  },
  {
    "case": "rho_0p0",
    "family": "MNL",
    "generated": {
      "model": "mnl",
      "N": 20000,
      "J": 5,
      "K": 12,
      "rho": 0.0,
      "random_coefficients": 0
    },
    "n_obs": 20000,
    "n_alternatives": 5,
    "n_variables": 12,
    "rho": 0.0,
    "n_parameters": 16,
    "parameters": [
      "B_X1",
      "B_X2",
      "B_X3",
      "B_X4",
      "B_X5",
      "B_X6",
      "B_X7",
      "B_X8",
      "B_X9",
      "B_X10",
      "B_X11",
      "B_X12",
      "ASC_ALT2",
      "ASC_ALT3",
      "ASC_ALT4",
      "ASC_ALT5"
    ],
    "consistent": "Yes",
    "runtime_policy": {
      "cpu_policy": "single-logical-core",
      "logical_cpu_affinity": [
        0
      ],
      "timing_scope": "estimation-plus-covariance",
      "thread_environment": {
        "OMP_NUM_THREADS": "1",
        "MKL_NUM_THREADS": "1",
        "OPENBLAS_NUM_THREADS": "1",
        "NUMEXPR_NUM_THREADS": "1",
        "BLIS_NUM_THREADS": "1",
        "VECLIB_MAXIMUM_THREADS": "1"
      },
      "xla_flags": "--xla_cpu_multi_thread_eigen=false intra_op_parallelism_threads=1",
      "torch_intraop_threads": 1,
      "torch_interop_threads": 1,
      "threadpools": [
        {
          "user_api": "openmp",
          "internal_api": "openmp",
          "num_threads": 1
        },
        {
          "user_api": "blas",
          "internal_api": "openblas",
          "num_threads": 1
        },
        {
          "user_api": "blas",
          "internal_api": "openblas",
          "num_threads": 1
        }
      ]
    },
    "backends": [
      {
        "backend": "torchdcm",
        "available": true,
        "total_s": 0.03880260977894068,
        "estimate_s": 0.02558326907455921,
        "covariance_s": 0.013219340704381466,
        "loglike": -15071.183022560796,
        "ll_diff": 0.0,
        "max_param_diff": 0.0,
        "max_prob_diff": 0.0,
        "max_cov_diff": 0.0,
        "max_se_diff": 0.0,
        "message": ""
      },
      {
        "backend": "scipy_bfgs",
        "available": true,
        "total_s": 27.616611623670906,
        "estimate_s": 27.60252231033519,
        "covariance_s": 0.014089313335716724,
        "loglike": -15071.183022560754,
        "ll_diff": 4.18367562815547E-11,
        "max_param_diff": 4.494717931180503E-8,
        "max_prob_diff": 2.55896777101583E-8,
        "max_cov_diff": 1.3907442363535194E-11,
        "max_se_diff": 2.2713831857035238E-10,
        "message": "Desired error not necessarily achieved due to precision loss."
      },
      {
        "backend": "biogeme",
        "available": true,
        "total_s": 5.681310110725462,
        "estimate_s": 5.681216681841761,
        "covariance_s": 0.00009342888370156288,
        "loglike": -15071.183023151501,
        "ll_diff": -5.907058948650956E-7,
        "max_param_diff": 0.000010674915374098148,
        "max_prob_diff": 0.000004602844384749005,
        "max_cov_diff": 8.402864249031083E-9,
        "max_se_diff": 1.3006250127595154E-7,
        "message": ""
      },
      {
        "backend": "apollo",
        "available": true,
        "total_s": 6.323,
        "estimate_s": 6.323,
        "covariance_s": 0,
        "loglike": -15071.183022560808,
        "ll_diff": -1.2732925824820995E-11,
        "max_param_diff": 7.470874685555629E-8,
        "max_prob_diff": 1.0072151268580853E-7,
        "max_cov_diff": 2.740610321148862E-11,
        "max_se_diff": 4.2420049417568606E-10,
        "message": "apollo_version=0.3.8"
      },
      {
        "backend": "mlogit",
        "available": true,
        "total_s": 1.1870000000000003,
        "estimate_s": 1.1860000000000004,
        "covariance_s": 0.0009999999999998899,
        "loglike": -15071.183022560792,
        "ll_diff": 3.637978807091713E-12,
        "max_param_diff": 4.581694296179606E-8,
        "max_prob_diff": 2.5037168671637744E-8,
        "max_cov_diff": 1.4939664197584357E-11,
        "max_se_diff": 2.4399671172403714E-10,
        "message": ""
      },
      {
        "backend": "gmnl",
        "available": true,
        "total_s": 14.028999999999998,
        "estimate_s": 14.028,
        "covariance_s": 0.0009999999999976694,
        "loglike": -15071.183022560792,
        "ll_diff": 3.637978807091713E-12,
        "max_param_diff": 4.581694301730721E-8,
        "max_prob_diff": 2.503716811652623E-8,
        "max_cov_diff": 1.510176586647788E-11,
        "max_se_diff": 2.466441773041339E-10,
        "message": ""
      },
      {
        "backend": "xlogit",
        "available": true,
        "total_s": 0.4381175171583891,
        "estimate_s": 0.4381170370616019,
        "covariance_s": 4.800967872142792E-7,
        "loglike": -15071.183022561443,
        "ll_diff": -6.475602276623249E-10,
        "max_param_diff": 5.457370217953894E-7,
        "max_prob_diff": 4.5017813143921614E-7,
        "max_cov_diff": 1.9004102230681802E-10,
        "max_se_diff": 3.0498281226865043E-9,
        "message": ""
      }
    ],
    "true_parameters": {
      "B_X1": -0.25,
      "B_X2": -0.32727272727272727,
      "B_X3": -0.40454545454545454,
      "B_X4": -0.48181818181818187,
      "B_X5": -0.5590909090909091,
      "B_X6": -0.6363636363636365,
      "B_X7": -0.7136363636363637,
      "B_X8": -0.790909090909091,
      "B_X9": -0.8681818181818183,
      "B_X10": -0.9454545454545455,
      "B_X11": -1.022727272727273,
      "B_X12": -1.1,
      "ASC_ALT2": -0.175,
      "ASC_ALT3": -0.35,
      "ASC_ALT4": -0.5249999999999999,
      "ASC_ALT5": -0.7
    }
  },
  {
    "case": "rho_0p5",
    "family": "MNL",
    "generated": {
      "model": "mnl",
      "N": 20000,
      "J": 5,
      "K": 12,
      "rho": 0.5,
      "random_coefficients": 0
    },
    "n_obs": 20000,
    "n_alternatives": 5,
    "n_variables": 12,
    "rho": 0.5,
    "n_parameters": 16,
    "parameters": [
      "B_X1",
      "B_X2",
      "B_X3",
      "B_X4",
      "B_X5",
      "B_X6",
      "B_X7",
      "B_X8",
      "B_X9",
      "B_X10",
      "B_X11",
      "B_X12",
      "ASC_ALT2",
      "ASC_ALT3",
      "ASC_ALT4",
      "ASC_ALT5"
    ],
    "consistent": "Yes",
    "runtime_policy": {
      "cpu_policy": "single-logical-core",
      "logical_cpu_affinity": [
        0
      ],
      "timing_scope": "estimation-plus-covariance",
      "thread_environment": {
        "OMP_NUM_THREADS": "1",
        "MKL_NUM_THREADS": "1",
        "OPENBLAS_NUM_THREADS": "1",
        "NUMEXPR_NUM_THREADS": "1",
        "BLIS_NUM_THREADS": "1",
        "VECLIB_MAXIMUM_THREADS": "1"
      },
      "xla_flags": "--xla_cpu_multi_thread_eigen=false intra_op_parallelism_threads=1",
      "torch_intraop_threads": 1,
      "torch_interop_threads": 1,
      "threadpools": [
        {
          "user_api": "openmp",
          "internal_api": "openmp",
          "num_threads": 1
        },
        {
          "user_api": "blas",
          "internal_api": "openblas",
          "num_threads": 1
        },
        {
          "user_api": "blas",
          "internal_api": "openblas",
          "num_threads": 1
        }
      ]
    },
    "backends": [
      {
        "backend": "torchdcm",
        "available": true,
        "total_s": 0.036509823985397816,
        "estimate_s": 0.02329869195818901,
        "covariance_s": 0.013211132027208805,
        "loglike": -6656.0320153090315,
        "ll_diff": 0.0,
        "max_param_diff": 0.0,
        "max_prob_diff": 0.0,
        "max_cov_diff": 0.0,
        "max_se_diff": 0.0,
        "message": ""
      },
      {
        "backend": "scipy_bfgs",
        "available": true,
        "total_s": 44.14106531534344,
        "estimate_s": 44.127070690039545,
        "covariance_s": 0.013994625303894281,
        "loglike": -6656.032015308823,
        "ll_diff": 2.0827428670600057E-10,
        "max_param_diff": 4.4347658922916366E-7,
        "max_prob_diff": 2.7973814425985566E-7,
        "max_cov_diff": 1.1816357224289642E-10,
        "max_se_diff": 1.28951387762255E-9,
        "message": "Desired error not necessarily achieved due to precision loss."
      },
      {
        "backend": "biogeme",
        "available": true,
        "total_s": 6.146195706445724,
        "estimate_s": 6.146105477120727,
        "covariance_s": 0.0000902293249964714,
        "loglike": -6656.03201646436,
        "ll_diff": -0.0000011553283911780454,
        "max_param_diff": 0.000020394482709962247,
        "max_prob_diff": 0.000008457740398593039,
        "max_cov_diff": 4.1004254707800725E-8,
        "max_se_diff": 4.3836039331779375E-7,
        "message": ""
      },
      {
        "backend": "apollo",
        "available": true,
        "total_s": 6.468999999999999,
        "estimate_s": 6.468999999999999,
        "covariance_s": 0,
        "loglike": -6656.032015309191,
        "ll_diff": -1.5916157281026244E-10,
        "max_param_diff": 4.953722074763078E-7,
        "max_prob_diff": 5.793077791915735E-7,
        "max_cov_diff": 3.205067483115498E-10,
        "max_se_diff": 3.5390591082706813E-9,
        "message": "apollo_version=0.3.8"
      },
      {
        "backend": "mlogit",
        "available": true,
        "total_s": 1.254,
        "estimate_s": 1.2530000000000001,
        "covariance_s": 0.0009999999999998899,
        "loglike": -6656.032015308856,
        "ll_diff": 1.7553247744217515E-10,
        "max_param_diff": 4.419251187215423E-7,
        "max_prob_diff": 2.8144393482421037E-7,
        "max_cov_diff": 1.183585078903815E-10,
        "max_se_diff": 1.3069233889551057E-9,
        "message": ""
      },
      {
        "backend": "gmnl",
        "available": true,
        "total_s": 17.618,
        "estimate_s": 17.616999999999997,
        "covariance_s": 0.0010000000000012221,
        "loglike": -6656.032015308856,
        "ll_diff": 1.7553247744217515E-10,
        "max_param_diff": 4.4192511727825234E-7,
        "max_prob_diff": 2.814439374332345E-7,
        "max_cov_diff": 1.1726256641045318E-10,
        "max_se_diff": 1.294821923292222E-9,
        "message": ""
      },
      {
        "backend": "xlogit",
        "available": true,
        "total_s": 0.4475262397900224,
        "estimate_s": 0.4475255198776722,
        "covariance_s": 7.199123501777649E-7,
        "loglike": -6656.032015317025,
        "ll_diff": -7.993548933882266E-9,
        "max_param_diff": 0.0000020456117564293663,
        "max_prob_diff": 0.000001664839242798699,
        "max_cov_diff": 3.1214345132084265E-9,
        "max_se_diff": 3.336988677049568E-8,
        "message": ""
      }
    ],
    "true_parameters": {
      "B_X1": -0.25,
      "B_X2": -0.32727272727272727,
      "B_X3": -0.40454545454545454,
      "B_X4": -0.48181818181818187,
      "B_X5": -0.5590909090909091,
      "B_X6": -0.6363636363636365,
      "B_X7": -0.7136363636363637,
      "B_X8": -0.790909090909091,
      "B_X9": -0.8681818181818183,
      "B_X10": -0.9454545454545455,
      "B_X11": -1.022727272727273,
      "B_X12": -1.1,
      "ASC_ALT2": -0.175,
      "ASC_ALT3": -0.35,
      "ASC_ALT4": -0.5249999999999999,
      "ASC_ALT5": -0.7
    }
  },
  {
    "case": "rho_0p98",
    "family": "MNL",
    "generated": {
      "model": "mnl",
      "N": 20000,
      "J": 5,
      "K": 12,
      "rho": 0.98,
      "random_coefficients": 0
    },
    "n_obs": 20000,
    "n_alternatives": 5,
    "n_variables": 12,
    "rho": 0.98,
    "n_parameters": 16,
    "parameters": [
      "B_X1",
      "B_X2",
      "B_X3",
      "B_X4",
      "B_X5",
      "B_X6",
      "B_X7",
      "B_X8",
      "B_X9",
      "B_X10",
      "B_X11",
      "B_X12",
      "ASC_ALT2",
      "ASC_ALT3",
      "ASC_ALT4",
      "ASC_ALT5"
    ],
    "consistent": "Yes",
    "runtime_policy": {
      "cpu_policy": "single-logical-core",
      "logical_cpu_affinity": [
        0
      ],
      "timing_scope": "estimation-plus-covariance",
      "thread_environment": {
        "OMP_NUM_THREADS": "1",
        "MKL_NUM_THREADS": "1",
        "OPENBLAS_NUM_THREADS": "1",
        "NUMEXPR_NUM_THREADS": "1",
        "BLIS_NUM_THREADS": "1",
        "VECLIB_MAXIMUM_THREADS": "1"
      },
      "xla_flags": "--xla_cpu_multi_thread_eigen=false intra_op_parallelism_threads=1",
      "torch_intraop_threads": 1,
      "torch_interop_threads": 1,
      "threadpools": [
        {
          "user_api": "openmp",
          "internal_api": "openmp",
          "num_threads": 1
        },
        {
          "user_api": "blas",
          "internal_api": "openblas",
          "num_threads": 1
        },
        {
          "user_api": "blas",
          "internal_api": "openblas",
          "num_threads": 1
        }
      ]
    },
    "backends": [
      {
        "backend": "torchdcm",
        "available": true,
        "total_s": 0.04756767814978957,
        "estimate_s": 0.03440106473863125,
        "covariance_s": 0.013166613411158323,
        "loglike": -5038.165750076262,
        "ll_diff": 0.0,
        "max_param_diff": 0.0,
        "max_prob_diff": 0.0,
        "max_cov_diff": 0.0,
        "max_se_diff": 0.0,
        "message": ""
      },
      {
        "backend": "scipy_bfgs",
        "available": true,
        "total_s": 20.52028316538781,
        "estimate_s": 20.506212379783392,
        "covariance_s": 0.014070785604417324,
        "loglike": -5038.1657500762485,
        "ll_diff": 1.3642420526593924E-11,
        "max_param_diff": 2.1832916508035538E-7,
        "max_prob_diff": 9.555535612770782E-8,
        "max_cov_diff": 1.7065036883590068E-10,
        "max_se_diff": 6.803168028923778E-10,
        "message": "Desired error not necessarily achieved due to precision loss."
      },
      {
        "backend": "biogeme",
        "available": true,
        "total_s": 6.438740595243871,
        "estimate_s": 6.438652606215328,
        "covariance_s": 0.00008798902854323387,
        "loglike": -5038.1657500878155,
        "ll_diff": -1.1553311196621507E-8,
        "max_param_diff": 0.000002382878256712573,
        "max_prob_diff": 9.766594668558781E-7,
        "max_cov_diff": 3.3968095530800824E-8,
        "max_se_diff": 1.3337887835862539E-7,
        "message": ""
      },
      {
        "backend": "apollo",
        "available": true,
        "total_s": 6.293000000000001,
        "estimate_s": 6.293000000000001,
        "covariance_s": 0,
        "loglike": -5038.165750076361,
        "ll_diff": -9.913492249324918E-11,
        "max_param_diff": 7.507768805536941E-7,
        "max_prob_diff": 3.213923114309125E-7,
        "max_cov_diff": 5.082202401973657E-10,
        "max_se_diff": 1.9942913986881194E-9,
        "message": "apollo_version=0.3.8"
      },
      {
        "backend": "mlogit",
        "available": true,
        "total_s": 1.2530000000000001,
        "estimate_s": 1.2520000000000002,
        "covariance_s": 0.0009999999999998899,
        "loglike": -5038.165750076252,
        "ll_diff": 1.000444171950221E-11,
        "max_param_diff": 2.945656061292823E-7,
        "max_prob_diff": 1.0950194873071695E-7,
        "max_cov_diff": 1.8891374575780162E-10,
        "max_se_diff": 7.531257839588079E-10,
        "message": ""
      },
      {
        "backend": "gmnl",
        "available": true,
        "total_s": 19.432,
        "estimate_s": 19.432,
        "covariance_s": 0.0,
        "loglike": -5038.165750076252,
        "ll_diff": 1.000444171950221E-11,
        "max_param_diff": 2.945656062403046E-7,
        "max_prob_diff": 1.0950194839765004E-7,
        "max_cov_diff": 1.9168017520443392E-10,
        "max_se_diff": 7.641544619296781E-10,
        "message": ""
      },
      {
        "backend": "xlogit",
        "available": true,
        "total_s": 0.4512027772143483,
        "estimate_s": 0.45120220724493265,
        "covariance_s": 5.699694156646729E-7,
        "loglike": -5038.165750096814,
        "ll_diff": -2.055185177596286E-8,
        "max_param_diff": 0.000011973428165112932,
        "max_prob_diff": 0.000004280691017544136,
        "max_cov_diff": 3.2111458537348314E-8,
        "max_se_diff": 1.260076458731163E-7,
        "message": ""
      }
    ],
    "true_parameters": {
      "B_X1": -0.25,
      "B_X2": -0.32727272727272727,
      "B_X3": -0.40454545454545454,
      "B_X4": -0.48181818181818187,
      "B_X5": -0.5590909090909091,
      "B_X6": -0.6363636363636365,
      "B_X7": -0.7136363636363637,
      "B_X8": -0.790909090909091,
      "B_X9": -0.8681818181818183,
      "B_X10": -0.9454545454545455,
      "B_X11": -1.022727272727273,
      "B_X12": -1.1,
      "ASC_ALT2": -0.175,
      "ASC_ALT3": -0.35,
      "ASC_ALT4": -0.5249999999999999,
      "ASC_ALT5": -0.7
    }
  }
]
