{
  "case": "nhts_2022_mode",
  "dataset_id": "nhts_2022",
  "model_name": "NHTS 2022 trip mode MNL",
  "n_obs": 27375,
  "n_alternatives": 5,
  "n_parameters": 16,
  "source": "NHTS 2022 official public-use CSV zip",
  "parameters": [
    "ASC_WALK",
    "B_LOG_MILES_WALK",
    "B_VEH_PER_ADULT_WALK",
    "B_URBAN_WALK",
    "ASC_BIKE",
    "B_LOG_MILES_BIKE",
    "B_VEH_PER_ADULT_BIKE",
    "B_URBAN_BIKE",
    "ASC_TRANSIT",
    "B_LOG_MILES_TRANSIT",
    "B_VEH_PER_ADULT_TRANSIT",
    "B_URBAN_TRANSIT",
    "ASC_OTHER",
    "B_LOG_MILES_OTHER",
    "B_VEH_PER_ADULT_OTHER",
    "B_URBAN_OTHER"
  ],
  "consistent": true,
  "backends": [
    {
      "backend": "torchdcm",
      "available": true,
      "total_s": 0.1210185126401484,
      "estimate_s": 0.10217503225430846,
      "covariance_s": 0.01884348038583994,
      "loglike": -19574.078199123112,
      "ll_diff": 0.0,
      "max_param_diff": 0.0,
      "max_prob_diff": 0.0,
      "max_cov_diff": 0.0,
      "max_se_diff": 0.0,
      "message": ""
    },
    {
      "backend": "biogeme",
      "available": true,
      "total_s": 1.7353912866674364,
      "estimate_s": 1.735298726707697,
      "covariance_s": 8.594989776611328e-05,
      "loglike": -19574.078199123025,
      "ll_diff": 8.731149137020111e-11,
      "max_param_diff": 3.922591885086035e-06,
      "max_prob_diff": 3.780852120272016e-07,
      "max_cov_diff": 1.3927134011326725e-07,
      "max_se_diff": 2.8907580393311427e-07,
      "message": ""
    }
  ]
}